swarmauri_signing_jws/JwsSignerVerifier.py
swarmauri_signing_jws/__init__.py
swarmauri_signing_jws-0.3.0.dev4.dist-info/LICENSE
swarmauri_signing_jws-0.3.0.dev4.dist-info/METADATA
swarmauri_signing_jws-0.3.0.dev4.dist-info/WHEEL
swarmauri_signing_jws-0.3.0.dev4.dist-info/entry_points.txt
swarmauri_signing_jws-0.3.0.dev4.dist-info/RECORD
