Metadata-Version: 2.3
Name: swarmauri_signing_jws
Version: 0.3.0.dev4
Summary: Composite JWS signer/verifier for Swarmauri
License: Apache-2.0
Author: Swarmauri
Author-email: opensource@swarmauri.com
Requires-Python: >=3.10,<3.13
Classifier: License :: OSI Approved :: Apache Software License
Classifier: Natural Language :: English
Classifier: Programming Language :: Python :: 3.10
Classifier: Programming Language :: Python :: 3.11
Classifier: Programming Language :: Python :: 3.12
Classifier: Programming Language :: Python :: 3.13
Classifier: Development Status :: 3 - Alpha
Classifier: Topic :: Security :: Cryptography
Classifier: Intended Audience :: Developers
Provides-Extra: cbor
Provides-Extra: secp256k1
Requires-Dist: cbor2 ; extra == "cbor"
Requires-Dist: swarmauri_base
Requires-Dist: swarmauri_core
Requires-Dist: swarmauri_signing_ecdsa
Requires-Dist: swarmauri_signing_ed25519
Requires-Dist: swarmauri_signing_hmac
Requires-Dist: swarmauri_signing_rsa
Requires-Dist: swarmauri_signing_secp256k1 ; extra == "secp256k1"
